candlestix/__init__.py
candlestix/candle_loader.py
candlestix/candleconf.py
candlestix/instrument.py
candlestix/time.py
candlestix/upstox.py
candlestix/tech/__init__.py
candlestix/tech/level_detector.py
candlestix/tech/srd_v2.py
candlestix/tech/srd_v3.py
candlestix/tech/trend.py
candlestix-2.0.4.dist-info/METADATA
candlestix-2.0.4.dist-info/WHEEL
candlestix-2.0.4.dist-info/top_level.txt
candlestix-2.0.4.dist-info/RECORD
