Metadata-Version: 2.4
Name: candlestix
Version: 2.0.4
Summary: Library to get candlesticks info
Home-page: https://github.com/sharmaak/candlestix
Author: Amit Kumar Sharma
Author-email: amit.official@gmail.com
Classifier: Development Status :: 4 - Beta
Classifier: Intended Audience :: Developers
Classifier: Programming Language :: Python :: 3
Classifier: Operating System :: POSIX :: Linux
Requires-Python: >=3.8
Requires-Dist: upstox-python-sdk>=2.4.0
Requires-Dist: pandas
Dynamic: author
Dynamic: author-email
Dynamic: classifier
Dynamic: description
Dynamic: description-content-type
Dynamic: home-page
Dynamic: requires-dist
Dynamic: requires-python
Dynamic: summary
